odoo/addons/portal_debranding/README.rst
odoo/addons/portal_debranding/__init__.py
odoo/addons/portal_debranding/__manifest__.py
odoo/addons/portal_debranding/i18n/de.po
odoo/addons/portal_debranding/i18n/it.po
odoo/addons/portal_debranding/i18n/portal_debranding.pot
odoo/addons/portal_debranding/readme/CONTRIBUTORS.md
odoo/addons/portal_debranding/readme/DESCRIPTION.md
odoo/addons/portal_debranding/static/description/icon.png
odoo/addons/portal_debranding/static/description/index.html
odoo/addons/portal_debranding/tests/__init__.py
odoo/addons/portal_debranding/tests/test_portal_debranding.py
odoo/addons/portal_debranding/views/portal_templates.xml
odoo/addons/portal_debranding/views/web_login_debrand.xml
odoo_addon_portal_debranding-19.0.1.0.0.8.dist-info/METADATA
odoo_addon_portal_debranding-19.0.1.0.0.8.dist-info/WHEEL
odoo_addon_portal_debranding-19.0.1.0.0.8.dist-info/top_level.txt
odoo_addon_portal_debranding-19.0.1.0.0.8.dist-info/RECORD
